termtris/__init__.py
termtris/__main__.py
termtris/board.py
termtris/cli.py
termtris/shapes.py
termtris/storage.py
termtris/ui.py
tetriskekw-0.11.0.dist-info/licenses/LICENSE
tetriskekw-0.11.0.dist-info/METADATA
tetriskekw-0.11.0.dist-info/WHEEL
tetriskekw-0.11.0.dist-info/entry_points.txt
tetriskekw-0.11.0.dist-info/top_level.txt
tetriskekw-0.11.0.dist-info/RECORD
