Metadata-Version: 2.4
Name: tetriskekw
Version: 0.11.0
Summary: A terminal Tetris game with persistent highscores (curses + SQLite)
Author-email: Shayan <tomohmmdali@gmail.com>
License: MIT License
Keywords: tetris,cli,game,terminal,python
Classifier: Programming Language :: Python :: 3
Classifier: License :: OSI Approved :: MIT License
Classifier: Operating System :: OS Independent
Requires-Python: >=3.8
License-File: LICENSE
Requires-Dist: platformdirs>=4.0
Requires-Dist: ltermio>=0.2.0
Requires-Dist: wcwidth>=0.2.5
Dynamic: license-file
